Goordinates/Gmap.py
Goordinates/__init__.py
Goordinates-1.0.3.dist-info/LICENSE
Goordinates-1.0.3.dist-info/METADATA
Goordinates-1.0.3.dist-info/WHEEL
Goordinates-1.0.3.dist-info/top_level.txt
Goordinates-1.0.3.dist-info/RECORD
